{
    "Max Nodes": 3782,
    "Max Edges": 8142,
    "Max Diameter": 19,
    "Fractal Num": 1811,
    "R² Abs Distribution": {
        ">= 0.05": 1810,
        ">= 0.10": 1810,
        ">= 0.15": 1810,
        ">= 0.20": 1808,
        ">= 0.25": 1807,
        ">= 0.30": 1804,
        ">= 0.35": 1803,
        ">= 0.40": 1801,
        ">= 0.45": 1800,
        ">= 0.50": 1798,
        ">= 0.55": 1795,
        ">= 0.60": 1791,
        ">= 0.65": 1788,
        ">= 0.70": 1781,
        ">= 0.75": 1772,
        ">= 0.80": 1748,
        ">= 0.85": 1665,
        ">= 0.90": 1523,
        ">= 0.95": 1127
    },
    "Diameter Distribution": {
        "< 5": 87,
        "5": 102,
        "6": 158,
        "7": 171,
        "8": 198,
        "9": 194,
        "10": 263,
        "11": 238,
        "12": 217,
        "13": 143,
        "14": 113,
        "15": 51,
        "16": 35,
        "17": 15,
        "18": 9,
        "19": 6
    }
}